gt_defect_dojo/__init__.py
gt_defect_dojo/defectdojo_apiv2.py
gt_defect_dojo-0.0.6.dist-info/METADATA
gt_defect_dojo-0.0.6.dist-info/WHEEL
gt_defect_dojo-0.0.6.dist-info/licenses/LICENSE
gt_defect_dojo-0.0.6.dist-info/RECORD
