Metadata-Version: 2.1
Name: gt-defect-dojo
Version: 0.0.6
Summary: An API wrapper for DefectDojo.
Project-URL: Homepage, https://github.com/gt-solutions/gt-defect-dojo
Project-URL: Bug Tracker, https://github.com/gt-solutions/gt-defect-dojo/issues
Author-email: Raito <raito.yagami.9x@gmail.com>
License: Copyright (c) 2018 The Python Packaging Authority
License-File: LICENSE
Classifier: License :: OSI Approved :: MIT License
Classifier: Operating System :: OS Independent
Classifier: Programming Language :: Python :: 3
Requires-Python: >=3.7
